windoz/World.py
windoz/__init__.py
windoz/windowsetting.py
windoz-0.0.8.dist-info/METADATA
windoz-0.0.8.dist-info/WHEEL
windoz-0.0.8.dist-info/licenses/LICENSE
windoz-0.0.8.dist-info/RECORD
